string_kit-1.0.0.dist-info/METADATA
string_kit-1.0.0.dist-info/WHEEL
string_kit-1.0.0.dist-info/entry_points.txt
string_kit-1.0.0.dist-info/licenses/LICENSE
string_kit/__init__.py
string_kit/formatter/__init__.py
string_kit/formatter/convertors.py
string_kit/formatter/formatter.py
string_kit/formatter/formatter_iterator.py
string_kit/version.py
string_kit-1.0.0.dist-info/RECORD
