Metadata-Version: 2.1
Name: string-kit
Version: 1.0.0
Summary: Library of string functions and formatters
Keywords: string formatter
Author-Email: "Aalap Shah (aka fishfin)" <shah.aalap@gmail.com>
License: MIT License
Classifier: Development Status :: 2 - Pre-Alpha
Classifier: Intended Audience :: Developers
Classifier: License :: OSI Approved :: MIT License
Classifier: Operating System :: OS Independent
Classifier: Programming Language :: Python :: 3
Classifier: Programming Language :: Python :: 3 :: Only
Classifier: Programming Language :: Python :: 3.12
Classifier: Programming Language :: Python :: 3.13
Classifier: Programming Language :: Python :: 3.14
Classifier: Topic :: Software Development
Classifier: Topic :: Utilities
Project-URL: Homepage, https://gitlab.com/shah-aalap/python-string-kit
Requires-Python: >=3.12
